mconv/__main__.py
mconv/libs.py
mconv/m_audio.py
mconv/m_probe.py
mconv/m_video.py
mconv/version.py
mconv-1.1.2.dist-info/LICENSE.txt
mconv-1.1.2.dist-info/METADATA
mconv-1.1.2.dist-info/WHEEL
mconv-1.1.2.dist-info/top_level.txt
mconv-1.1.2.dist-info/RECORD
