Metadata-Version: 2.1
Name: mconv
Version: 1.1.2
Summary: Multimedia library maintainer
Home-page: https://github.com/gllera/mconv
Author: Gabriel Llera
Author-email: g113r4@gmail.com
License: UNKNOWN
Platform: UNKNOWN
Classifier: Programming Language :: Python :: 3
Classifier: License :: OSI Approved :: MIT License
Classifier: Operating System :: OS Independent
Requires-Python: >=3.6
